odoo/addons/stock_dynamic_routing/README.rst
odoo/addons/stock_dynamic_routing/__init__.py
odoo/addons/stock_dynamic_routing/__manifest__.py
odoo/addons/stock_dynamic_routing/demo/stock_location_demo.xml
odoo/addons/stock_dynamic_routing/demo/stock_picking_type_demo.xml
odoo/addons/stock_dynamic_routing/demo/stock_routing_demo.xml
odoo/addons/stock_dynamic_routing/i18n/es_AR.po
odoo/addons/stock_dynamic_routing/i18n/it.po
odoo/addons/stock_dynamic_routing/i18n/stock_dynamic_routing.pot
odoo/addons/stock_dynamic_routing/models/__init__.py
odoo/addons/stock_dynamic_routing/models/stock_location.py
odoo/addons/stock_dynamic_routing/models/stock_move.py
odoo/addons/stock_dynamic_routing/models/stock_picking.py
odoo/addons/stock_dynamic_routing/models/stock_routing.py
odoo/addons/stock_dynamic_routing/models/stock_routing_rule.py
odoo/addons/stock_dynamic_routing/readme/CONFIGURE.rst
odoo/addons/stock_dynamic_routing/readme/CONTRIBUTORS.rst
odoo/addons/stock_dynamic_routing/readme/DESCRIPTION.rst
odoo/addons/stock_dynamic_routing/readme/USAGE.rst
odoo/addons/stock_dynamic_routing/security/ir.model.access.csv
odoo/addons/stock_dynamic_routing/static/description/icon.png
odoo/addons/stock_dynamic_routing/static/description/index.html
odoo/addons/stock_dynamic_routing/tests/__init__.py
odoo/addons/stock_dynamic_routing/tests/test_routing_pull.py
odoo/addons/stock_dynamic_routing/tests/test_routing_push.py
odoo/addons/stock_dynamic_routing/tests/test_routing_rule.py
odoo/addons/stock_dynamic_routing/views/stock_routing_views.xml
odoo14_addon_stock_dynamic_routing-14.0.1.1.2.dist-info/METADATA
odoo14_addon_stock_dynamic_routing-14.0.1.1.2.dist-info/WHEEL
odoo14_addon_stock_dynamic_routing-14.0.1.1.2.dist-info/top_level.txt
odoo14_addon_stock_dynamic_routing-14.0.1.1.2.dist-info/RECORD
